ut_com/__init__.py
ut_com/__version__.py
ut_com/com.py
ut_com/dec.py
ut_com/py.typed
ut_com/timer.py
ut_com-2.0.0.20251020.dist-info/licenses/LICENSE.txt
ut_com-2.0.0.20251020.dist-info/METADATA
ut_com-2.0.0.20251020.dist-info/WHEEL
ut_com-2.0.0.20251020.dist-info/top_level.txt
ut_com-2.0.0.20251020.dist-info/RECORD
