Metadata-Version: 2.4
Name: ut_com
Version: 2.0.0.20251020
Summary: Utilities for Communication
Author: Bernd Stroehle
Author-email: bernd.stroehle@gmail.com
Maintainer: Bernd Stroehle
Maintainer-email: bernd.stroehle@gmail.com
License-Expression: GPL-3.0-only WITH Classpath-exception-2.0 OR BSD-3-Clause
Project-URL: Source Code, https://github.com/bs29/ut_com/tree/master
Project-URL: Homepage, https://kosakya.de/
Project-URL: Documentation, https://ka-com.readthedocs.io/en/latest
Project-URL: Apache-2.0 License, https://apache.org/licenses/LICENSE-2.0
Project-URL: GPLv3 License, https://www.gnu.org/licenses/gpl-3.0.en.html
Classifier: Development Status :: 5 - Production/Stable
Classifier: Intended Audience :: Developers
Classifier: Operating System :: OS Independent
Classifier: Programming Language :: Python :: 3.11
Classifier: Natural Language :: English
Classifier: Topic :: Software Development :: Libraries :: Python Modules
Requires-Python: >=3.10
License-File: LICENSE.txt
Requires-Dist: numpy>=2.3.4
Requires-Dist: ut_cli>=2.0.2.20251017
Requires-Dist: ut_log>=1.3.7.20251017
Requires-Dist: ut_pac>=1.3.1.20251018
Dynamic: license-file
